faster_tokenizers/__init__.py
faster_tokenizers/commit.log
faster_tokenizers/core_tokenizers.so
faster_tokenizers/libicudata.so.70
faster_tokenizers/libicuuc.so.70
faster_tokenizers/models/__init__.py
faster_tokenizers/normalizers/__init__.py
faster_tokenizers/postprocessors/__init__.py
faster_tokenizers/pretokenizers/__init__.py
faster_tokenizers/tokenizers_impl/__init__.py
faster_tokenizers/tokenizers_impl/base_tokenizer.py
faster_tokenizers/tokenizers_impl/ernie.py
faster_tokenizers-0.1.1.dist-info/METADATA
faster_tokenizers-0.1.1.dist-info/WHEEL
faster_tokenizers-0.1.1.dist-info/top_level.txt
faster_tokenizers-0.1.1.dist-info/RECORD
